LICENSE
MANIFEST.in
README
README.rst
setup.py
src/django_monkey_team.egg-info/PKG-INFO
src/django_monkey_team.egg-info/SOURCES.txt
src/django_monkey_team.egg-info/dependency_links.txt
src/django_monkey_team.egg-info/not-zip-safe
src/django_monkey_team.egg-info/requires.txt
src/django_monkey_team.egg-info/top_level.txt
src/monkey_team/__init__.py
src/monkey_team/admin.py
src/monkey_team/aes.js
src/monkey_team/forms.py
src/monkey_team/middleware.py
src/monkey_team/models.py
src/monkey_team/tests.py
src/monkey_team/utils.py
src/monkey_team/views.py
src/monkey_team/static/monkey_team/google-chrome.png
src/monkey_team/templates/monkey-team.user.js
src/monkey_team/templates/monkey_500.html
src/monkey_team/templates/monkey_decode.html
src/monkey_team/templates/monkey_setup.html
tests/test_project/__init__.py
tests/test_project/__init__.pyc
tests/test_project/database.sqlite
tests/test_project/settings.py
tests/test_project/settings.py.bak
tests/test_project/settings.pyc
tests/test_project/urls.py
tests/test_project/urls.pyc
tests/test_project/templates/404.html
tests/test_project/templates/500.html