Metadata-Version: 1.1
Name: django-monkey-team
Version: 0.2.2
Summary: Django middleware that displays debug tracebacks on production sites (where you would have `DEBUG = False`) only to developers.
Home-page: https://github.com/ionelmc/django-monkey-team
Author: Ionel Cristian Mărieș
Author-email: contact@ionelmc.ro
License: BSD
Platform: UNKNOWN
Classifier: Development Status :: 4 - Beta
Classifier: Framework :: Django
Classifier: Intended Audience :: Developers
Classifier: License :: OSI Approved :: BSD License
Classifier: Operating System :: OS Independent
Classifier: Programming Language :: Python
Classifier: Topic :: Internet :: WWW/HTTP
Classifier: Programming Language :: Python :: 2.6
Classifier: Programming Language :: Python :: 2.7
Classifier: Programming Language :: Python :: 2 :: Only
Classifier: Programming Language :: Python :: Implementation :: CPython
